fibsem_metadata/__init__.py
fibsem_metadata/classes.py
fibsem_metadata/dataset.py
fibsem_metadata/index.py
fibsem_metadata/multiscale/__init__.py
fibsem_metadata/multiscale/cosem.py
fibsem_metadata/multiscale/neuroglancer.py
fibsem_metadata-0.1.3.dist-info/WHEEL
fibsem_metadata-0.1.3.dist-info/METADATA
fibsem_metadata-0.1.3.dist-info/RECORD
